ssb_libtest3/__init__.py
ssb_libtest3/__main__.py
ssb_libtest3/functions.py
ssb_libtest3/py.typed
ssb_libtest3-0.0.1.dist-info/LICENSE
ssb_libtest3-0.0.1.dist-info/METADATA
ssb_libtest3-0.0.1.dist-info/WHEEL
ssb_libtest3-0.0.1.dist-info/entry_points.txt
ssb_libtest3-0.0.1.dist-info/RECORD
